numbers_lib/__init__.py
numbers_lib/netnumbr.py
netnumbrpkgabc-0.0.1.dist-info/METADATA
netnumbrpkgabc-0.0.1.dist-info/WHEEL
netnumbrpkgabc-0.0.1.dist-info/top_level.txt
netnumbrpkgabc-0.0.1.dist-info/RECORD
